pyninja/__init__.py
pyninja/main.py
pyninja/startup.py
pyninja/version.py
pyninja/executors/auth.py
pyninja/executors/database.py
pyninja/executors/routers.py
pyninja/executors/squire.py
pyninja/features/application.py
pyninja/features/certificates.py
pyninja/features/dockerized.py
pyninja/features/operations.py
pyninja/features/process.py
pyninja/features/service.py
pyninja/features/zipper.py
pyninja/modules/cache.py
pyninja/modules/enums.py
pyninja/modules/exceptions.py
pyninja/modules/models.py
pyninja/modules/payloads.py
pyninja/modules/rate_limit.py
pyninja/modules/secure.py
pyninja/modules/tree.py
pyninja/modules/templates/api/mfa_template.html
pyninja/modules/templates/api/run_ui.html
pyninja/modules/templates/api/swaggerUI.js
pyninja/modules/templates/monitor/disk_report_darwin.html
pyninja/modules/templates/monitor/disk_report_linux.html
pyninja/modules/templates/monitor/index.html
pyninja/modules/templates/monitor/logout.html
pyninja/modules/templates/monitor/main.html
pyninja/modules/templates/monitor/session.html
pyninja/modules/templates/monitor/unauthorized.html
pyninja/monitor/__init__.py
pyninja/monitor/authenticator.py
pyninja/monitor/config.py
pyninja/monitor/drive.py
pyninja/monitor/resources.py
pyninja/monitor/routes.py
pyninja/multifactor/gmail.py
pyninja/multifactor/mfa.py
pyninja/multifactor/ntfy.py
pyninja/multifactor/otp.py
pyninja/multifactor/telegram.py
pyninja/routes/certificates.py
pyninja/routes/commands.py
pyninja/routes/download.py
pyninja/routes/fullaccess.py
pyninja/routes/ipaddr.py
pyninja/routes/metrics.py
pyninja/routes/namespace.py
pyninja/routes/observability.py
pyninja/routes/orchestration.py
pyninja/routes/upload.py
pyninja-4.9.9.dist-info/licenses/LICENSE
pyninja-4.9.9.dist-info/METADATA
pyninja-4.9.9.dist-info/WHEEL
pyninja-4.9.9.dist-info/entry_points.txt
pyninja-4.9.9.dist-info/top_level.txt
pyninja-4.9.9.dist-info/RECORD
