Metadata-Version: 2.4
Name: PyNinja
Version: 4.9.9
Summary: Lightweight OS-agnostic service monitoring API
Author-email: Vignesh Rao <svignesh1793@gmail.com>
License: MIT License
Project-URL: Homepage, https://github.com/thevickypedia/PyNinja
Project-URL: Docs, https://thevickypedia.github.io/PyNinja
Project-URL: Source, https://github.com/thevickypedia/PyNinja
Project-URL: Bug Tracker, https://github.com/thevickypedia/PyNinja/issues
Project-URL: Release Notes, https://github.com/thevickypedia/PyNinja/blob/main/release_notes.rst
Keywords: system-monitor,PyNinja
Classifier: License :: OSI Approved :: MIT License
Classifier: Programming Language :: Python :: 3
Classifier: Development Status :: 5 - Production/Stable
Classifier: Operating System :: MacOS :: MacOS X
Classifier: Operating System :: Microsoft :: Windows
Classifier: Operating System :: POSIX :: Linux
Classifier: Topic :: System :: Monitoring
Requires-Python: >=3.11
License-File: LICENSE
Requires-Dist: click==8.1.*
Requires-Dist: cryptography==45.0.*
Requires-Dist: docker==7.1.*
Requires-Dist: fastapi==0.116.*
Requires-Dist: gmail-connector==1.0.*
Requires-Dist: Jinja2==3.1.*
Requires-Dist: psutil==6.0.*
Requires-Dist: PyArchitecture==0.3.*
Requires-Dist: pydantic==2.*
Requires-Dist: pydantic-settings==2.*
Requires-Dist: pyotp==2.9.*
Requires-Dist: python-multipart>=0.0.19
Requires-Dist: PyUdisk==2.0.*
Requires-Dist: PyYaml==6.0.*
Requires-Dist: qrcode[pil]==8.*
Requires-Dist: requests==2.*
Requires-Dist: uvicorn[standard]==0.35.*
Provides-Extra: dev
Requires-Dist: sphinx==5.1.1; extra == "dev"
Requires-Dist: pre-commit; extra == "dev"
Requires-Dist: recommonmark; extra == "dev"
Requires-Dist: gitverse; extra == "dev"
Requires-Dist: aiohttp==3.12.*; extra == "dev"
Requires-Dist: python-dotenv==1.1.*; extra == "dev"
Requires-Dist: tqdm==4.67.*; extra == "dev"
Requires-Dist: requests==2.*; extra == "dev"
Dynamic: license-file
